cbs_analyzer/__init__.py
cbs_analyzer/cbs_analyzer.py
cbs_analyzer/cbs_utils/__init__.py
cbs_analyzer/cbs_utils/core_analyzers.py
cbs_analyzer/cbs_utils/core_exporter.py
cbs_analyzer/cbs_utils/core_handlers.py
cbs_analyzer/cbs_utils/exceptions.py
cbs_analyzer/cbs_utils/type_hints.py
cbs_analyzer/cbs_utils/utils.py
cbs_analyzer/cbs_utils/wrappers.py
cbs_analyzer-1.0.0.dist-info/licenses/LICENSE.md
cbs_analyzer-1.0.0.dist-info/METADATA
cbs_analyzer-1.0.0.dist-info/WHEEL
cbs_analyzer-1.0.0.dist-info/top_level.txt
cbs_analyzer-1.0.0.dist-info/RECORD
